bagofstuff/__init__.py
bagofstuff/itertools.py
bagofstuff/pipe.py
bagofstuff/py.typed
bagofstuff-0.1.0.dist-info/WHEEL
bagofstuff-0.1.0.dist-info/METADATA
bagofstuff-0.1.0.dist-info/RECORD
