Metadata-Version: 2.4
Name: bagofstuff
Version: 0.1.0
Summary: davep's general Python utility library
Keywords: library
Author: Dave Pearson
Author-email: Dave Pearson <davep@davep.org>
License-Expression: MIT
Classifier: Development Status :: 3 - Alpha
Classifier: Operating System :: OS Independent
Classifier: Programming Language :: Python :: 3 :: Only
Classifier: Programming Language :: Python :: 3.12
Classifier: Programming Language :: Python :: 3.13
Classifier: Programming Language :: Python :: 3.14
Classifier: Topic :: Software Development :: Libraries
Classifier: Typing :: Typed
Requires-Python: >=3.12
